setup.py
CW_stegano.egg-info/PKG-INFO
CW_stegano.egg-info/SOURCES.txt
CW_stegano.egg-info/dependency_links.txt
CW_stegano.egg-info/top_level.txt
steganography/__init__.py