Metadata-Version: 1.0
Name: CW-stegano
Version: 1.0.7
Summary: A fun little python script that encodes and decodes strings and images
Home-page: https://github.com/CalderWhite/steganography
Author: Calder White
Author-email: calderwhite1@gmail.com
License: UNKNOWN
Platform: UNKNOWN
